transfv/__init__.py
transfv/__main__.py
transfv/argument.py
transfv/arguments.py
transfv/configuration.py
transfv/constants.py
transfv/events.py
transfv/history.py
transfv/languages.py
transfv/obj.py
transfv/prints.py
transfv/thirdside.py
transfv/translator.py
transfv-1.0.9.dist-info/LICENSE
transfv-1.0.9.dist-info/METADATA
transfv-1.0.9.dist-info/WHEEL
transfv-1.0.9.dist-info/entry_points.txt
transfv-1.0.9.dist-info/top_level.txt
transfv-1.0.9.dist-info/RECORD
