Metadata-Version: 2.1
Name: transfv
Version: 1.0.9
Summary: Google translator for a terminal.
Home-page: https://github.com/filipvrba/trans.git
Author: Filip Vrba
Author-email: filipvrba@pm.me
License: MIT
Keywords: python,google,translator,fv,transfv
Classifier: Development Status :: 5 - Production/Stable
Classifier: Intended Audience :: Education
Classifier: Operating System :: OS Independent
Classifier: License :: OSI Approved :: MIT License
Classifier: Programming Language :: Python :: 3
Classifier: Programming Language :: Python :: 3.5
Classifier: Programming Language :: Python :: 3.6
Classifier: Programming Language :: Python :: 3.7
Classifier: Programming Language :: Python :: 3.8
License-File: LICENSE
Requires-Dist: googletrans (==4.0.0-rc1)
